MANIFEST.in
README.rst
pyproject.toml
setup.cfg
setup.py
django_telemetrics.egg-info/PKG-INFO
django_telemetrics.egg-info/SOURCES.txt
django_telemetrics.egg-info/dependency_links.txt
django_telemetrics.egg-info/requires.txt
django_telemetrics.egg-info/top_level.txt
django_telemetry/__init__.py
django_telemetry/admin.py
django_telemetry/apps.py
django_telemetry/middleware.py
django_telemetry/models.py
django_telemetry/routers.py
django_telemetry/tests.py
django_telemetry/urls.py
django_telemetry/views.py
django_telemetry/migrations/0001_initial.py
django_telemetry/migrations/__init__.py
django_telemetry/static/.DS_Store
django_telemetry/static/telemetry/css/app.css
django_telemetry/static/telemetry/img/logo.png
django_telemetry/templates/.DS_Store
django_telemetry/templates/layouts/telemetry/app.html
django_telemetry/templates/telemetry/.DS_Store
django_telemetry/templates/telemetry/detail_request.html
django_telemetry/templates/telemetry/main.html